ait_dsn-2.0.0-py3.7-nspkg.pth
ait/dsn/__init__.py
ait/dsn/bch/__init__.py
ait/dsn/bch/bch.py
ait/dsn/bch/test/__init__.py
ait/dsn/bch/test/bch_test.py
ait/dsn/bin/__init__.py
ait/dsn/bin/ait_cfdp_mock_server.py
ait/dsn/bin/ait_cfdp_start_sender.py
ait/dsn/bin/ait_sle_bridge.py
ait/dsn/bin/ait_sle_interface_manager.py
ait/dsn/cfdp/__init__.py
ait/dsn/cfdp/cfdp.py
ait/dsn/cfdp/events.py
ait/dsn/cfdp/exceptions.py
ait/dsn/cfdp/mib.py
ait/dsn/cfdp/primitives.py
ait/dsn/cfdp/request.py
ait/dsn/cfdp/timer.py
ait/dsn/cfdp/util.py
ait/dsn/cfdp/machines/__init__.py
ait/dsn/cfdp/machines/machine.py
ait/dsn/cfdp/machines/receiver1.py
ait/dsn/cfdp/machines/sender1.py
ait/dsn/cfdp/pdu/__init__.py
ait/dsn/cfdp/pdu/eof.py
ait/dsn/cfdp/pdu/filedata.py
ait/dsn/cfdp/pdu/header.py
ait/dsn/cfdp/pdu/md.py
ait/dsn/cfdp/pdu/pdu.py
ait/dsn/cfdp/pdu/util.py
ait/dsn/cfdp/test/__init__.py
ait/dsn/cfdp/test/cfdp_test.py
ait/dsn/cfdp/test/pdu_test.py
ait/dsn/proc/__init__.py
ait/dsn/proc/deframe_packet_processor.py
ait/dsn/proc/test/__init__.py
ait/dsn/proc/test/frame_generator_test.py
ait/dsn/proc/test/run_modulo_list.py
ait/dsn/sle/__init__.py
ait/dsn/sle/cltu.py
ait/dsn/sle/common.py
ait/dsn/sle/frames.py
ait/dsn/sle/raf.py
ait/dsn/sle/rcf.py
ait/dsn/sle/util.py
ait/dsn/sle/pdu/__init__.py
ait/dsn/sle/pdu/binds.py
ait/dsn/sle/pdu/common.py
ait/dsn/sle/pdu/raf.py
ait/dsn/sle/pdu/rcf.py
ait/dsn/sle/pdu/service_instance.py
ait/dsn/sle/pdu/cltu/__init__.py
ait/dsn/sle/pdu/cltu/cltuv4.py
ait/dsn/sle/pdu/cltu/cltuv5.py
ait/dsn/sle/pdu/cltu/common.py
ait/dsn/sle/test/__init__.py
ait/dsn/sle/test/frames_test.py
ait_dsn-2.0.0.dist-info/LICENSE.txt
ait_dsn-2.0.0.dist-info/METADATA
ait_dsn-2.0.0.dist-info/WHEEL
ait_dsn-2.0.0.dist-info/entry_points.txt
ait_dsn-2.0.0.dist-info/namespace_packages.txt
ait_dsn-2.0.0.dist-info/top_level.txt
ait_dsn-2.0.0.dist-info/RECORD
