Metadata-Version: 2.1
Name: ait-dsn
Version: 2.0.0
Summary: AIT DSN provides APIs for connecting to the Deep Space Network (DSN) via the Space Link Extension interfaces.
Home-page: https://github.com/NASA-AMMOS/AIT-DSN
Author: AIT Development Team
Author-email: ait-pmc@googlegroups.com
License: UNKNOWN
Platform: UNKNOWN
Requires-Dist: greenlet (==0.4.16)
Requires-Dist: ait-core (>=2.0.0)
Requires-Dist: pyasn1
Provides-Extra: docs
Requires-Dist: Sphinx ; extra == 'docs'
Requires-Dist: sphinx-rtd-theme ; extra == 'docs'
Requires-Dist: sphinxcontrib-httpdomain ; extra == 'docs'
Provides-Extra: tests
Requires-Dist: nose ; extra == 'tests'
Requires-Dist: coverage ; extra == 'tests'
Requires-Dist: mock ; extra == 'tests'
Requires-Dist: pylint ; extra == 'tests'
